{
  "name": {
    "tr": "IQF Soğan Halka",
    "en": "",
    "ar": "",
    "de": "",
    "ja": "",
    "ko": ""
  },
  "status": "play",
  "category": "c16iqfseb",
  "id": "5q2e66uuy6",
  "externalUrl": "",
  "path": "iqf-sogan-halka",
  "keyword": {
    "tr": "Tillo Kochari, Gaziantep, doğal gıda, IQF Soğan Halka, IQF Dilimlenmiş Sebzeler, IQF sebze, dondurulmuş sebze, endüstriyel sebze, dilim sebze",
    "en": "",
    "ar": "",
    "de": "",
    "ja": "",
    "ko": ""
  },
  "description": {
    "tr": "Tillo Kochari IQF Soğan Halka: Soğan halka. IQF Dilimlenmiş Sebzeler grubunda. Sunulan gramaj: 10 kg. Gaziantep kökenli doğal gıda.",
    "en": "",
    "ar": "",
    "de": "",
    "ja": "",
    "ko": ""
  },
  "index": 142,
  "icon": "ac_unit",
  "desing": {
    "header": [],
    "body": [],
    "footer": []
  },
  "desc": {
    "gramaj": "10 kg",
    "ambalaj": "",
    "mensei": "Türkiye"
  },
  "title": {
    "tr": "IQF Soğan Halka | Tillo Kochari",
    "en": "",
    "ar": "",
    "de": "",
    "ja": "",
    "ko": ""
  },
  "text": {
    "tr": "",
    "en": "",
    "ar": "",
    "de": "",
    "ja": "",
    "ko": ""
  },
  "update": "2026-05-21T08:40:07.752Z",
  "date": "2026-05-20T09:54:46.018Z",
  "img": "index.webp"
}
