{
  "name": {
    "tr": "Süt ve Süt Ürünleri",
    "en": "",
    "ar": "",
    "de": "",
    "ja": "",
    "ko": ""
  },
  "status": "play",
  "category": "",
  "id": "c12sut",
  "externalUrl": "",
  "path": "sut-ve-sut-urunleri",
  "keyword": {
    "tr": "Tillo Kochari, Gaziantep, doğal gıda, Süt ve Süt Ürünleri, süt ürünleri, kaşar peynir, beyaz peynir, tereyağı, yoğurt",
    "en": "",
    "ar": "",
    "de": "",
    "ja": "",
    "ko": ""
  },
  "description": {
    "tr": "Tillo Kochari Süt ve Süt Ürünleri. Süt ve süt ürünleri: peynir, tereyağı, kaymak, yoğurt, ayran. Tereyağı, peynir, yoğurt ve geleneksel süt ürünleri. Gaziant…",
    "en": "",
    "ar": "",
    "de": "",
    "ja": "",
    "ko": ""
  },
  "index": 11,
  "icon": "category",
  "desing": {
    "header": [],
    "body": [],
    "footer": []
  },
  "desc": {},
  "title": {
    "tr": "Süt ve Süt Ürünleri Ürünleri | Tillo Kochari",
    "en": "",
    "ar": "",
    "de": "",
    "ja": "",
    "ko": ""
  },
  "text": {
    "tr": "",
    "en": "",
    "ar": "",
    "de": "",
    "ja": "",
    "ko": ""
  },
  "update": "2026-05-21T08:39:29.741Z",
  "date": "2026-05-20T09:54:46.237Z",
  "categorypage": "products"
}